setup.py
call_seq_browser/__init__.py
call_seq_browser/browser.py
call_seq_browser/main.py
call_seq_browser.egg-info/PKG-INFO
call_seq_browser.egg-info/SOURCES.txt
call_seq_browser.egg-info/dependency_links.txt
call_seq_browser.egg-info/pbr.json
call_seq_browser.egg-info/requires.txt
call_seq_browser.egg-info/top_level.txt
call_seq_browser/TextEdit/__init__.py
call_seq_browser/TextEdit/rich.py
call_seq_browser/Widgets/InfoWidgetWrapper.py
call_seq_browser/Widgets/JsonWidgetWrapper.py
call_seq_browser/Widgets/__init__.py